rtl_sv/dla_pe.sv
`timescale 1ns / 1ps

// Processing Element (PE): accumulates a*b when enabled.
module dla_pe #(
    parameter int DATA_W = 8,
    parameter int ACC_W  = 24
) (
    input  logic                     clk,
    input  logic                     rst_n,
    input  logic                     clear,
    input  logic                     en,
    input  logic signed [DATA_W-1:0] a_in,
    input  logic signed [DATA_W-1:0] b_in,
    output logic signed [ACC_W-1:0]  acc_out
);

    logic signed [(2*DATA_W)-1:0] mult_res;
    logic signed [ACC_W-1:0]      mult_ext;

    // Multiply in DATA_W domain, then sign-extend to accumulator width.
    assign mult_res = a_in * b_in;
    assign mult_ext = {{(ACC_W-(2*DATA_W)){mult_res[(2*DATA_W)-1]}}, mult_res};

    // Synchronous clear + accumulate datapath.
    always_ff @(posedge clk or negedge rst_n) begin
        if (!rst_n) begin
            acc_out <= '0;
        end else if (clear) begin
            acc_out <= '0;
        end else if (en) begin
            acc_out <= acc_out + mult_ext;
        end
    end

endmodule

tb/dla_pe_tb.sv
`timescale 1ns / 1ps

module dla_pe_tb;

    localparam int DATA_W = 8;
    localparam int ACC_W  = 24;

    logic                     clk;
    logic                     rst_n;
    logic                     clear;
    logic                     en;
    logic signed [DATA_W-1:0] a_in;
    logic signed [DATA_W-1:0] b_in;
    logic signed [ACC_W-1:0]  acc_out;

    integer errors;

    dla_pe #(
        .DATA_W(DATA_W),
        .ACC_W(ACC_W)
    ) dut (
        .clk(clk),
        .rst_n(rst_n),
        .clear(clear),
        .en(en),
        .a_in(a_in),
        .b_in(b_in),
        .acc_out(acc_out)
    );

    always #5 clk = ~clk;

    task automatic apply_cycle(
        input logic clear_i,
        input logic en_i,
        input int a_i,
        input int b_i
    );
        begin
            @(negedge clk);
            clear <= clear_i;
            en    <= en_i;
            a_in  <= $signed(a_i);
            b_in  <= $signed(b_i);
            @(posedge clk);
            #1;
        end
    endtask

    task automatic expect_acc(input int step_id, input int expected);
        begin
            if ($signed(acc_out) !== expected) begin
                errors = errors + 1;
                $display(
                    "[TB][FAIL][step=%0d] acc_out=%0d expected=%0d",
                    step_id,
                    $signed(acc_out),
                    expected
                );
            end
        end
    endtask

    initial begin
        $dumpfile("sim/results/dla_pe_tb.vcd");
        $dumpvars(0, dla_pe_tb);

        clk    = 1'b0;
        rst_n  = 1'b0;
        clear  = 1'b0;
        en     = 1'b0;
        a_in   = '0;
        b_in   = '0;
        errors = 0;

        repeat (3) @(posedge clk);
        rst_n = 1'b1;
        @(posedge clk);
        #1;
        expect_acc(0, 0);

        apply_cycle(1'b1, 1'b1, 5, 6);   // clear has priority over accumulate
        expect_acc(1, 0);

        apply_cycle(1'b0, 1'b1, 2, 3);   // +6
        expect_acc(2, 6);

        apply_cycle(1'b0, 1'b1, -4, 2);  // -8, total = -2
        expect_acc(3, -2);

        apply_cycle(1'b0, 1'b0, 7, 7);   // hold value
        expect_acc(4, -2);

        apply_cycle(1'b1, 1'b0, 0, 0);   // clear
        expect_acc(5, 0);

        if (errors == 0) begin
            $display("[TB][PASS] dla_pe_tb passed.");
            $finish;
        end else begin
            $display("[TB][ERROR] dla_pe_tb mismatches=%0d", errors);
            $fatal(1);
        end
    end

endmodule

sim/results/dla_pe_tb.vcd
$date
	Sun Apr 19 06:06:25 2026
$end
$version
	Icarus Verilog
$end
$timescale
	1ps
$end
$scope module dla_pe_tb $end
$var wire 24 ! acc_out [23:0] $end
$var parameter 32 " ACC_W $end
$var parameter 32 # DATA_W $end
$var reg 8 $ a_in [7:0] $end
$var reg 8 % b_in [7:0] $end
$var reg 1 & clear $end
$var reg 1 ' clk $end
$var reg 1 ( en $end
$var reg 1 ) rst_n $end
$var integer 32 * errors [31:0] $end
$scope module dut $end
$var wire 8 + a_in [7:0] $end
$var wire 8 , b_in [7:0] $end
$var wire 1 & clear $end
$var wire 1 ' clk $end
$var wire 1 ( en $end
$var wire 1 ) rst_n $end
$var wire 16 - mult_res [15:0] $end
$var wire 24 . mult_ext [23:0] $end
$var parameter 32 / ACC_W $end
$var parameter 32 0 DATA_W $end
$var reg 24 1 acc_out [23:0] $end
$upscope $end
$scope task apply_cycle $end
$upscope $end
$scope task expect_acc $end
$upscope $end
$upscope $end
$enddefinitions $end
$comment Show the parameter values. $end
$dumpall
b1000 0
b11000 /
b1000 #
b11000 "
$end
#0
$dumpvars
b0 1
b0 .
b0 -
b0 ,
b0 +
b0 *
0)
0(
0'
0&
b0 %
b0 $
b0 !
$end
#5000
1'
#10000
0'
#15000
1'
#20000
0'
#25000
1)
1'
#30000
0'
#35000
1'
#40000
b11110 .
b11110 -
b110 %
b110 ,
b101 $
b101 +
1(
1&
0'
#45000
1'
#50000
b11 %
b11 ,
b110 .
b110 -
b10 $
b10 +
0&
0'
#55000
b110 !
b110 1
1'
#60000
b10 %
b10 ,
b111111111111111111111000 .
b1111111111111000 -
b11111100 $
b11111100 +
0'
#65000
b111111111111111111111110 !
b111111111111111111111110 1
1'
#70000
b111 %
b111 ,
b110001 .
b110001 -
b111 $
b111 +
0(
0'
#75000
1'
#80000
b0 %
b0 ,
b0 .
b0 -
b0 $
b0 +
1&
0'
#85000
b0 !
b0 1
1'
