GCollab/rtl/dla_a_buffer_bank.v
`timescale 1ns / 1ps

// A buffer stores matrix A as [row][k] and returns a full row-vector at rd_col=k.
module dla_a_buffer_bank #(
    parameter N       = 4,
    parameter K       = 4,
    parameter DATA_W  = 8,
    parameter ADDR_W  = (N*K <= 1) ? 1 : $clog2(N*K),
    parameter K_IDX_W = (K <= 1) ? 1 : $clog2(K)
) (
    input                            clk,
    input                            wr_en,
    input [ADDR_W-1:0]               wr_addr,
    input signed [DATA_W-1:0]        wr_data,
    input [K_IDX_W-1:0]              rd_col,
    output reg signed [(N*DATA_W)-1:0] row_vector
);

    reg signed [DATA_W-1:0] mem [0:(N*K)-1];

    integer i;

    // Single-port synchronous write using linearized row-major addressing.
    always @(posedge clk) begin
        if (wr_en) begin
            mem[wr_addr] <= wr_data;
        end
    end

    // Combinational read: gather A[0..N-1][rd_col] into row_vector.
    always @* begin
        row_vector = {(N*DATA_W){1'b0}};
        for (i = 0; i < N; i = i + 1) begin
            row_vector[(i*DATA_W) +: DATA_W] = mem[(i*K) + rd_col];
        end
    end

endmodule

tb/dla_a_buffer_bank_tb.sv
`timescale 1ns / 1ps

module dla_a_buffer_bank_tb;

    localparam int N       = 3;
    localparam int K       = 4;
    localparam int DATA_W  = 8;
    localparam int ADDR_W  = (N*K <= 1) ? 1 : $clog2(N*K);
    localparam int K_IDX_W = (K <= 1) ? 1 : $clog2(K);

    logic                         clk;
    logic                         wr_en;
    logic [ADDR_W-1:0]            wr_addr;
    logic signed [DATA_W-1:0]     wr_data;
    logic [K_IDX_W-1:0]           rd_col;
    logic signed [(N*DATA_W)-1:0] row_vector;

    integer A [0:N-1][0:K-1];
    integer errors;
    integer i;
    integer k;

    dla_a_buffer_bank #(
        .N(N),
        .K(K),
        .DATA_W(DATA_W),
        .ADDR_W(ADDR_W),
        .K_IDX_W(K_IDX_W)
    ) dut (
        .clk(clk),
        .wr_en(wr_en),
        .wr_addr(wr_addr),
        .wr_data(wr_data),
        .rd_col(rd_col),
        .row_vector(row_vector)
    );

    always #5 clk = ~clk;

    task automatic write_a(input int row, input int col, input int value);
        begin
            @(negedge clk);
            wr_en   <= 1'b1;
            wr_addr <= ((row*K) + col);
            wr_data <= $signed(value);

            @(negedge clk);
            wr_en   <= 1'b0;
            wr_addr <= '0;
            wr_data <= '0;
        end
    endtask

    function automatic integer lane_value(input int lane_idx);
        begin
            lane_value = $signed(row_vector[(lane_idx*DATA_W) +: DATA_W]);
        end
    endfunction

    initial begin
        $dumpfile("sim/results/dla_a_buffer_bank_tb.vcd");
        $dumpvars(0, dla_a_buffer_bank_tb);

        clk    = 1'b0;
        wr_en  = 1'b0;
        wr_addr = '0;
        wr_data = '0;
        rd_col  = '0;
        errors  = 0;

        A[0][0] = 1;  A[0][1] = -2; A[0][2] = 3;  A[0][3] = -4;
        A[1][0] = 5;  A[1][1] = 6;  A[1][2] = -7; A[1][3] = 8;
        A[2][0] = -1; A[2][1] = 2;  A[2][2] = -3; A[2][3] = 4;

        for (i = 0; i < N; i = i + 1) begin
            for (k = 0; k < K; k = k + 1) begin
                write_a(i, k, A[i][k]);
            end
        end

        for (k = 0; k < K; k = k + 1) begin
            rd_col = k[K_IDX_W-1:0];
            #1;

            for (i = 0; i < N; i = i + 1) begin
                if (lane_value(i) !== A[i][k]) begin
                    errors = errors + 1;
                    $display(
                        "[TB][FAIL] rd_col=%0d lane=%0d value=%0d expected=%0d",
                        k,
                        i,
                        lane_value(i),
                        A[i][k]
                    );
                end
            end

            @(posedge clk);
        end

        if (errors == 0) begin
            $display("[TB][PASS] dla_a_buffer_bank_tb passed.");
            $finish;
        end else begin
            $display("[TB][ERROR] dla_a_buffer_bank_tb mismatches=%0d", errors);
            $fatal(1);
        end
    end

endmodule

sim/results/dla_a_buffer_bank_tb.vcd
$date
	Sun Apr 19 06:06:24 2026
$end
$version
	Icarus Verilog
$end
$timescale
	1ps
$end
$scope module dla_a_buffer_bank_tb $end
$var wire 24 ! row_vector [23:0] $end
$var parameter 32 " ADDR_W $end
$var parameter 32 # DATA_W $end
$var parameter 32 $ K $end
$var parameter 32 % K_IDX_W $end
$var parameter 32 & N $end
$var reg 1 ' clk $end
$var reg 2 ( rd_col [1:0] $end
$var reg 4 ) wr_addr [3:0] $end
$var reg 8 * wr_data [7:0] $end
$var reg 1 + wr_en $end
$var integer 32 , errors [31:0] $end
$var integer 32 - i [31:0] $end
$var integer 32 . k [31:0] $end
$scope function lane_value $end
$upscope $end
$scope module dut $end
$var wire 1 ' clk $end
$var wire 2 / rd_col [1:0] $end
$var wire 4 0 wr_addr [3:0] $end
$var wire 8 1 wr_data [7:0] $end
$var wire 1 + wr_en $end
$var parameter 32 2 ADDR_W $end
$var parameter 32 3 DATA_W $end
$var parameter 32 4 K $end
$var parameter 32 5 K_IDX_W $end
$var parameter 32 6 N $end
$var reg 24 7 row_vector [23:0] $end
$var integer 32 8 i [31:0] $end
$upscope $end
$scope task write_a $end
$upscope $end
$upscope $end
$enddefinitions $end
$comment Show the parameter values. $end
$dumpall
b11 6
b10 5
b100 4
b1000 3
b100 2
b11 &
b10 %
b100 $
b1000 #
b100 "
$end
#0
$dumpvars
b11 8
bx 7
b0 1
b0 0
b0 /
b0 .
b0 -
b0 ,
0+
b0 *
b0 )
b0 (
0'
bx !
$end
#5000
1'
#10000
b1 *
b1 1
1+
0'
#15000
b11 8
bx00000001 !
bx00000001 7
1'
#20000
b0 *
b0 1
0+
b1 .
0'
#25000
1'
#30000
b11111110 *
b11111110 1
b1 )
b1 0
1+
0'
#35000
b11 8
bx00000001 !
bx00000001 7
1'
#40000
b0 *
b0 1
b0 )
b0 0
0+
b10 .
0'
#45000
1'
#50000
b11 *
b11 1
b10 )
b10 0
1+
0'
#55000
b11 8
bx00000001 !
bx00000001 7
1'
#60000
b0 *
b0 1
b0 )
b0 0
0+
b11 .
0'
#65000
1'
#70000
b11111100 *
b11111100 1
b11 )
b11 0
1+
0'
#75000
b11 8
bx00000001 !
bx00000001 7
1'
#80000
b0 *
b0 1
b0 )
b0 0
0+
b1 -
b0 .
0'
#85000
1'
#90000
b101 *
b101 1
b100 )
b100 0
1+
0'
#95000
b11 8
bx0000010100000001 !
bx0000010100000001 7
1'
#100000
b0 *
b0 1
b0 )
b0 0
0+
b1 .
0'
#105000
1'
#110000
b110 *
b110 1
b101 )
b101 0
1+
0'
#115000
b11 8
bx0000010100000001 !
bx0000010100000001 7
1'
#120000
b0 *
b0 1
b0 )
b0 0
0+
b10 .
0'
#125000
1'
#130000
b11111001 *
b11111001 1
b110 )
b110 0
1+
0'
#135000
b11 8
bx0000010100000001 !
bx0000010100000001 7
1'
#140000
b0 *
b0 1
b0 )
b0 0
0+
b11 .
0'
#145000
1'
#150000
b1000 *
b1000 1
b111 )
b111 0
1+
0'
#155000
b11 8
bx0000010100000001 !
bx0000010100000001 7
1'
#160000
b0 *
b0 1
b0 )
b0 0
0+
b10 -
b0 .
0'
#165000
1'
#170000
b11111111 *
b11111111 1
b1000 )
b1000 0
1+
0'
#175000
b11 8
b111111110000010100000001 !
b111111110000010100000001 7
1'
#180000
b0 *
b0 1
b0 )
b0 0
0+
b1 .
0'
#185000
1'
#190000
b10 *
b10 1
b1001 )
b1001 0
1+
0'
#195000
b11 8
b111111110000010100000001 !
b111111110000010100000001 7
1'
#200000
b0 *
b0 1
b0 )
b0 0
0+
b10 .
0'
#205000
1'
#210000
b11111101 *
b11111101 1
b1010 )
b1010 0
1+
0'
#215000
b11 8
b111111110000010100000001 !
b111111110000010100000001 7
1'
#220000
b0 *
b0 1
b0 )
b0 0
0+
b11 .
0'
#225000
1'
#230000
b100 *
b100 1
b1011 )
b1011 0
1+
0'
#235000
b11 8
b111111110000010100000001 !
b111111110000010100000001 7
1'
#240000
b0 *
b0 1
b0 )
b0 0
0+
b11 -
b0 .
0'
#241000
b11 -
#245000
b11 8
b100000011011111110 !
b100000011011111110 7
b1 (
b1 /
b1 .
1'
#246000
b11 -
#250000
0'
#255000
b11 8
b111111011111100100000011 !
b111111011111100100000011 7
b10 (
b10 /
b10 .
1'
#256000
b11 -
#260000
0'
#265000
b11 8
b1000000100011111100 !
b1000000100011111100 7
b11 (
b11 /
b11 .
1'
#266000
b11 -
#270000
0'
#275000
b100 .
1'
