rtl_sv/dla_pe.sv
`timescale 1ns / 1ps

// Processing Element (PE): accumulates a*b when enabled.
module dla_pe #(
    parameter int DATA_W = 8,
    parameter int ACC_W  = 24
) (
    input  logic                     clk,
    input  logic                     rst_n,
    input  logic                     clear,
    input  logic                     en,
    input  logic signed [DATA_W-1:0] a_in,
    input  logic signed [DATA_W-1:0] b_in,
    output logic signed [ACC_W-1:0]  acc_out
);

    logic signed [(2*DATA_W)-1:0] mult_res;
    logic signed [ACC_W-1:0]      mult_ext;

    // Multiply in DATA_W domain, then sign-extend to accumulator width.
    assign mult_res = a_in * b_in;
    assign mult_ext = {{(ACC_W-(2*DATA_W)){mult_res[(2*DATA_W)-1]}}, mult_res};

    // Synchronous clear + accumulate datapath.
    always_ff @(posedge clk or negedge rst_n) begin
        if (!rst_n) begin
            acc_out <= '0;
        end else if (clear) begin
            acc_out <= '0;
        end else if (en) begin
            acc_out <= acc_out + mult_ext;
        end
    end

endmodule

rtl/dla_pe_array.v
`timescale 1ns / 1ps

// N x N PE grid. Each PE receives one A row element and one B column element.
module dla_pe_array #(
    parameter N      = 4,
    parameter DATA_W = 8,
    parameter ACC_W  = 24
) (
    input                              clk,
    input                              rst_n,
    input                              clear,
    input                              en,
    input signed [(N*DATA_W)-1:0]      a_bus,
    input signed [(N*DATA_W)-1:0]      b_bus,
    output signed [(N*N*ACC_W)-1:0]    c_bus
);

    genvar i;
    genvar j;

    generate
        // Instantiate the PE matrix and repack each accumulator into c_bus.
        for (i = 0; i < N; i = i + 1) begin : GEN_PE_ROWS
            for (j = 0; j < N; j = j + 1) begin : GEN_PE_COLS
                localparam FLAT_IDX = (i*N) + j;
                wire signed [ACC_W-1:0] acc_val;

                dla_pe #(
                    .DATA_W(DATA_W),
                    .ACC_W(ACC_W)
                ) u_pe (
                    .clk(clk),
                    .rst_n(rst_n),
                    .clear(clear),
                    .en(en),
                    .a_in(a_bus[(i*DATA_W) +: DATA_W]),
                    .b_in(b_bus[(j*DATA_W) +: DATA_W]),
                    .acc_out(acc_val)
                );

                assign c_bus[(FLAT_IDX*ACC_W) +: ACC_W] = acc_val;
            end
        end
    endgenerate

endmodule

tb/dla_pe_array_tb.sv
`timescale 1ns / 1ps

module dla_pe_array_tb;

    localparam int N      = 2;
    localparam int DATA_W = 8;
    localparam int ACC_W  = 24;

    logic                           clk;
    logic                           rst_n;
    logic                           clear;
    logic                           en;
    logic signed [(N*DATA_W)-1:0]   a_bus;
    logic signed [(N*DATA_W)-1:0]   b_bus;
    logic signed [(N*N*ACC_W)-1:0]  c_bus;

    integer errors;

    dla_pe_array #(
        .N(N),
        .DATA_W(DATA_W),
        .ACC_W(ACC_W)
    ) dut (
        .clk(clk),
        .rst_n(rst_n),
        .clear(clear),
        .en(en),
        .a_bus(a_bus),
        .b_bus(b_bus),
        .c_bus(c_bus)
    );

    always #5 clk = ~clk;

    task automatic drive_cycle(
        input logic clear_i,
        input logic en_i,
        input logic signed [(N*DATA_W)-1:0] a_i,
        input logic signed [(N*DATA_W)-1:0] b_i
    );
        begin
            @(negedge clk);
            clear <= clear_i;
            en    <= en_i;
            a_bus <= a_i;
            b_bus <= b_i;
            @(posedge clk);
            #1;
        end
    endtask

    function automatic integer c_at(input int row, input int col);
        int flat_idx;
        begin
            flat_idx = (row*N) + col;
            c_at = $signed(c_bus[(flat_idx*ACC_W) +: ACC_W]);
        end
    endfunction

    task automatic expect_c(input int row, input int col, input int expected);
        integer actual;
        begin
            actual = c_at(row, col);
            if (actual !== expected) begin
                errors = errors + 1;
                $display(
                    "[TB][FAIL] C[%0d][%0d]=%0d expected=%0d",
                    row,
                    col,
                    actual,
                    expected
                );
            end
        end
    endtask

    initial begin
        $dumpfile("sim/results/dla_pe_array_tb.vcd");
        $dumpvars(0, dla_pe_array_tb);

        clk    = 1'b0;
        rst_n  = 1'b0;
        clear  = 1'b0;
        en     = 1'b0;
        a_bus  = '0;
        b_bus  = '0;
        errors = 0;

        repeat (3) @(posedge clk);
        rst_n = 1'b1;

        // Reset accumulators once before compute.
        drive_cycle(1'b1, 1'b0, '0, '0);

        // Cycle 0: a=[1,2], b=[3,4]
        drive_cycle(1'b0, 1'b1, {8'sd2, 8'sd1}, {8'sd4, 8'sd3});

        // Cycle 1: a=[-1,0], b=[2,-2]
        drive_cycle(1'b0, 1'b1, {8'sd0, -8'sd1}, {-8'sd2, 8'sd2});

        // Cycle 2: a=[3,1], b=[1,5]
        drive_cycle(1'b0, 1'b1, {8'sd1, 8'sd3}, {8'sd5, 8'sd1});

        // Hold for one cycle and check final accumulators.
        drive_cycle(1'b0, 1'b0, '0, '0);

        // Expected matrix:
        // [ 4, 21 ]
        // [ 7, 13 ]
        expect_c(0, 0, 4);
        expect_c(0, 1, 21);
        expect_c(1, 0, 7);
        expect_c(1, 1, 13);

        if (errors == 0) begin
            $display("[TB][PASS] dla_pe_array_tb passed.");
            $finish;
        end else begin
            $display("[TB][ERROR] dla_pe_array_tb mismatches=%0d", errors);
            $fatal(1);
        end
    end

endmodule

sim/results/dla_pe_array_tb.vcd
$date
	Sun Apr 19 06:06:24 2026
$end
$version
	Icarus Verilog
$end
$timescale
	1ps
$end
$scope module dla_pe_array_tb $end
$var wire 96 ! c_bus [95:0] $end
$var parameter 32 " ACC_W $end
$var parameter 32 # DATA_W $end
$var parameter 32 $ N $end
$var reg 16 % a_bus [15:0] $end
$var reg 16 & b_bus [15:0] $end
$var reg 1 ' clear $end
$var reg 1 ( clk $end
$var reg 1 ) en $end
$var reg 1 * rst_n $end
$var integer 32 + errors [31:0] $end
$scope function c_at $end
$upscope $end
$scope module dut $end
$var wire 16 , a_bus [15:0] $end
$var wire 16 - b_bus [15:0] $end
$var wire 1 ' clear $end
$var wire 1 ( clk $end
$var wire 1 ) en $end
$var wire 1 * rst_n $end
$var wire 96 . c_bus [95:0] $end
$var parameter 32 / ACC_W $end
$var parameter 32 0 DATA_W $end
$var parameter 32 1 N $end
$scope begin GEN_PE_ROWS[0] $end
$var parameter 2 2 i $end
$scope begin GEN_PE_COLS[0] $end
$var wire 24 3 acc_val [23:0] $end
$var parameter 32 4 FLAT_IDX $end
$var parameter 2 5 j $end
$scope module u_pe $end
$var wire 8 6 a_in [7:0] $end
$var wire 8 7 b_in [7:0] $end
$var wire 1 ' clear $end
$var wire 1 ( clk $end
$var wire 1 ) en $end
$var wire 1 * rst_n $end
$var wire 16 8 mult_res [15:0] $end
$var wire 24 9 mult_ext [23:0] $end
$var parameter 32 : ACC_W $end
$var parameter 32 ; DATA_W $end
$var reg 24 < acc_out [23:0] $end
$upscope $end
$upscope $end
$scope begin GEN_PE_COLS[1] $end
$var wire 24 = acc_val [23:0] $end
$var parameter 32 > FLAT_IDX $end
$var parameter 2 ? j $end
$scope module u_pe $end
$var wire 8 @ a_in [7:0] $end
$var wire 8 A b_in [7:0] $end
$var wire 1 ' clear $end
$var wire 1 ( clk $end
$var wire 1 ) en $end
$var wire 1 * rst_n $end
$var wire 16 B mult_res [15:0] $end
$var wire 24 C mult_ext [23:0] $end
$var parameter 32 D ACC_W $end
$var parameter 32 E DATA_W $end
$var reg 24 F acc_out [23:0] $end
$upscope $end
$upscope $end
$upscope $end
$scope begin GEN_PE_ROWS[1] $end
$var parameter 2 G i $end
$scope begin GEN_PE_COLS[0] $end
$var wire 24 H acc_val [23:0] $end
$var parameter 32 I FLAT_IDX $end
$var parameter 2 J j $end
$scope module u_pe $end
$var wire 8 K a_in [7:0] $end
$var wire 8 L b_in [7:0] $end
$var wire 1 ' clear $end
$var wire 1 ( clk $end
$var wire 1 ) en $end
$var wire 1 * rst_n $end
$var wire 16 M mult_res [15:0] $end
$var wire 24 N mult_ext [23:0] $end
$var parameter 32 O ACC_W $end
$var parameter 32 P DATA_W $end
$var reg 24 Q acc_out [23:0] $end
$upscope $end
$upscope $end
$scope begin GEN_PE_COLS[1] $end
$var wire 24 R acc_val [23:0] $end
$var parameter 32 S FLAT_IDX $end
$var parameter 2 T j $end
$scope module u_pe $end
$var wire 8 U a_in [7:0] $end
$var wire 8 V b_in [7:0] $end
$var wire 1 ' clear $end
$var wire 1 ( clk $end
$var wire 1 ) en $end
$var wire 1 * rst_n $end
$var wire 16 W mult_res [15:0] $end
$var wire 24 X mult_ext [23:0] $end
$var parameter 32 Y ACC_W $end
$var parameter 32 Z DATA_W $end
$var reg 24 [ acc_out [23:0] $end
$upscope $end
$upscope $end
$upscope $end
$upscope $end
$scope task drive_cycle $end
$upscope $end
$scope task expect_c $end
$upscope $end
$upscope $end
$enddefinitions $end
$comment Show the parameter values. $end
$dumpall
b1000 Z
b11000 Y
b1 T
b11 S
b1000 P
b11000 O
b0 J
b10 I
b1 G
b1000 E
b11000 D
b1 ?
b1 >
b1000 ;
b11000 :
b0 5
b0 4
b0 2
b10 1
b1000 0
b11000 /
b10 $
b1000 #
b11000 "
$end
#0
$dumpvars
b0 [
b0 X
b0 W
b0 V
b0 U
b0 R
b0 Q
b0 N
b0 M
b0 L
b0 K
b0 H
b0 F
b0 C
b0 B
b0 A
b0 @
b0 =
b0 <
b0 9
b0 8
b0 7
b0 6
b0 3
b0 .
b0 -
b0 ,
b0 +
0*
0)
0(
0'
b0 &
b0 %
b0 !
$end
#5000
1(
#10000
0(
#15000
1(
#20000
0(
#25000
1*
1(
#30000
1'
0(
#35000
1(
#40000
b11 9
b11 8
b11 7
b100 C
b100 B
b100 A
b110 N
b110 M
b11 L
b1000 X
b1000 W
b100 V
b1 6
b1 @
b10 K
b10 U
b10000000011 &
b10000000011 -
b1000000001 %
b1000000001 ,
1)
0'
0(
#45000
b1000 R
b1000 [
b110 H
b110 Q
b100 =
b100 F
b1000000000000000000000000110000000000000000000000100000000000000000000000011 !
b1000000000000000000000000110000000000000000000000100000000000000000000000011 .
b11 3
b11 <
1(
#50000
b10 7
b11111110 A
b10 L
b11111110 V
b111111111111111111111110 9
b1111111111111110 8
b11111111 6
b10 C
b10 B
b11111111 @
b0 N
b0 M
b0 K
b0 X
b0 W
b0 U
b1111111000000010 &
b1111111000000010 -
b11111111 %
b11111111 ,
0(
#55000
b1 3
b1 <
b1000000000000000000000000110000000000000000000000110000000000000000000000001 !
b1000000000000000000000000110000000000000000000000110000000000000000000000001 .
b110 =
b110 F
1(
#60000
b1 7
b101 A
b1 L
b101 V
b11 9
b11 8
b11 6
b1111 C
b1111 B
b11 @
b1 N
b1 M
b1 K
b101 X
b101 W
b1 U
b10100000001 &
b10100000001 -
b100000011 %
b100000011 ,
0(
#65000
b1101 R
b1101 [
b111 H
b111 Q
b10101 =
b10101 F
b1101000000000000000000000111000000000000000000010101000000000000000000000100 !
b1101000000000000000000000111000000000000000000010101000000000000000000000100 .
b100 3
b100 <
1(
#70000
b0 7
b0 A
b0 L
b0 V
b0 9
b0 8
b0 6
b0 C
b0 B
b0 @
b0 N
b0 M
b0 K
b0 X
b0 W
b0 U
b0 &
b0 -
b0 %
b0 ,
0)
0(
