rtl/dla_b_buffer_bank.v
`timescale 1ns / 1ps

// B buffer stores matrix B as [k][col] and returns a full k-row at rd_row=k.
module dla_b_buffer_bank #(
    parameter N       = 4,
    parameter K       = 4,
    parameter DATA_W  = 8,
    parameter ADDR_W  = (N*K <= 1) ? 1 : $clog2(N*K),
    parameter K_IDX_W = (K <= 1) ? 1 : $clog2(K)
) (
    input                            clk,
    input                            wr_en,
    input [ADDR_W-1:0]               wr_addr,
    input signed [DATA_W-1:0]        wr_data,
    input [K_IDX_W-1:0]              rd_row,
    output reg signed [(N*DATA_W)-1:0] col_vector
);

    reg signed [DATA_W-1:0] mem [0:(N*K)-1];

    integer j;

    // Single-port synchronous write using linearized row-major addressing.
    always @(posedge clk) begin
        if (wr_en) begin
            mem[wr_addr] <= wr_data;
        end
    end

    // Combinational read: gather B[rd_row][0..N-1] into col_vector.
    always @* begin
        col_vector = {(N*DATA_W){1'b0}};
        for (j = 0; j < N; j = j + 1) begin
            col_vector[(j*DATA_W) +: DATA_W] = mem[(rd_row*N) + j];
        end
    end

endmodule

tb/dla_b_buffer_bank_tb.sv
`timescale 1ns / 1ps

module dla_b_buffer_bank_tb;

    localparam int N       = 3;
    localparam int K       = 4;
    localparam int DATA_W  = 8;
    localparam int ADDR_W  = (N*K <= 1) ? 1 : $clog2(N*K);
    localparam int K_IDX_W = (K <= 1) ? 1 : $clog2(K);

    logic                         clk;
    logic                         wr_en;
    logic [ADDR_W-1:0]            wr_addr;
    logic signed [DATA_W-1:0]     wr_data;
    logic [K_IDX_W-1:0]           rd_row;
    logic signed [(N*DATA_W)-1:0] col_vector;

    integer B [0:K-1][0:N-1];
    integer errors;
    integer r;
    integer c;

    dla_b_buffer_bank #(
        .N(N),
        .K(K),
        .DATA_W(DATA_W),
        .ADDR_W(ADDR_W),
        .K_IDX_W(K_IDX_W)
    ) dut (
        .clk(clk),
        .wr_en(wr_en),
        .wr_addr(wr_addr),
        .wr_data(wr_data),
        .rd_row(rd_row),
        .col_vector(col_vector)
    );

    always #5 clk = ~clk;

    task automatic write_b(input int row, input int col, input int value);
        begin
            @(negedge clk);
            wr_en   <= 1'b1;
            wr_addr <= ((row*N) + col);
            wr_data <= $signed(value);

            @(negedge clk);
            wr_en   <= 1'b0;
            wr_addr <= '0;
            wr_data <= '0;
        end
    endtask

    function automatic integer lane_value(input int lane_idx);
        begin
            lane_value = $signed(col_vector[(lane_idx*DATA_W) +: DATA_W]);
        end
    endfunction

    initial begin
        $dumpfile("sim/results/dla_b_buffer_bank_tb.vcd");
        $dumpvars(0, dla_b_buffer_bank_tb);

        clk     = 1'b0;
        wr_en   = 1'b0;
        wr_addr = '0;
        wr_data = '0;
        rd_row  = '0;
        errors  = 0;

        B[0][0] = 1;  B[0][1] = -1; B[0][2] = 2;
        B[1][0] = 3;  B[1][1] = 4;  B[1][2] = -5;
        B[2][0] = -2; B[2][1] = 6;  B[2][2] = 7;
        B[3][0] = 8;  B[3][1] = -3; B[3][2] = 0;

        for (r = 0; r < K; r = r + 1) begin
            for (c = 0; c < N; c = c + 1) begin
                write_b(r, c, B[r][c]);
            end
        end

        for (r = 0; r < K; r = r + 1) begin
            rd_row = r[K_IDX_W-1:0];
            #1;

            for (c = 0; c < N; c = c + 1) begin
                if (lane_value(c) !== B[r][c]) begin
                    errors = errors + 1;
                    $display(
                        "[TB][FAIL] rd_row=%0d lane=%0d value=%0d expected=%0d",
                        r,
                        c,
                        lane_value(c),
                        B[r][c]
                    );
                end
            end

            @(posedge clk);
        end

        if (errors == 0) begin
            $display("[TB][PASS] dla_b_buffer_bank_tb passed.");
            $finish;
        end else begin
            $display("[TB][ERROR] dla_b_buffer_bank_tb mismatches=%0d", errors);
            $fatal(1);
        end
    end

endmodule

sim/results/dla_b_buffer_bank_tb.vcd
$date
	Sun Apr 19 06:06:24 2026
$end
$version
	Icarus Verilog
$end
$timescale
	1ps
$end
$scope module dla_b_buffer_bank_tb $end
$var wire 24 ! col_vector [23:0] $end
$var parameter 32 " ADDR_W $end
$var parameter 32 # DATA_W $end
$var parameter 32 $ K $end
$var parameter 32 % K_IDX_W $end
$var parameter 32 & N $end
$var reg 1 ' clk $end
$var reg 2 ( rd_row [1:0] $end
$var reg 4 ) wr_addr [3:0] $end
$var reg 8 * wr_data [7:0] $end
$var reg 1 + wr_en $end
$var integer 32 , c [31:0] $end
$var integer 32 - errors [31:0] $end
$var integer 32 . r [31:0] $end
$scope function lane_value $end
$upscope $end
$scope module dut $end
$var wire 1 ' clk $end
$var wire 2 / rd_row [1:0] $end
$var wire 4 0 wr_addr [3:0] $end
$var wire 8 1 wr_data [7:0] $end
$var wire 1 + wr_en $end
$var parameter 32 2 ADDR_W $end
$var parameter 32 3 DATA_W $end
$var parameter 32 4 K $end
$var parameter 32 5 K_IDX_W $end
$var parameter 32 6 N $end
$var reg 24 7 col_vector [23:0] $end
$var integer 32 8 j [31:0] $end
$upscope $end
$scope task write_b $end
$upscope $end
$upscope $end
$enddefinitions $end
$comment Show the parameter values. $end
$dumpall
b11 6
b10 5
b100 4
b1000 3
b100 2
b11 &
b10 %
b100 $
b1000 #
b100 "
$end
#0
$dumpvars
b11 8
bx 7
b0 1
b0 0
b0 /
b0 .
b0 -
b0 ,
0+
b0 *
b0 )
b0 (
0'
bx !
$end
#5000
1'
#10000
b1 *
b1 1
1+
0'
#15000
b11 8
bx00000001 !
bx00000001 7
1'
#20000
b0 *
b0 1
0+
b1 ,
0'
#25000
1'
#30000
b11111111 *
b11111111 1
b1 )
b1 0
1+
0'
#35000
b11 8
bx1111111100000001 !
bx1111111100000001 7
1'
#40000
b0 *
b0 1
b0 )
b0 0
0+
b10 ,
0'
#45000
1'
#50000
b10 *
b10 1
b10 )
b10 0
1+
0'
#55000
b11 8
b101111111100000001 !
b101111111100000001 7
1'
#60000
b0 *
b0 1
b0 )
b0 0
0+
b1 .
b0 ,
0'
#65000
1'
#70000
b11 *
b11 1
b11 )
b11 0
1+
0'
#75000
b11 8
b101111111100000001 !
b101111111100000001 7
1'
#80000
b0 *
b0 1
b0 )
b0 0
0+
b1 ,
0'
#85000
1'
#90000
b100 *
b100 1
b100 )
b100 0
1+
0'
#95000
b11 8
b101111111100000001 !
b101111111100000001 7
1'
#100000
b0 *
b0 1
b0 )
b0 0
0+
b10 ,
0'
#105000
1'
#110000
b11111011 *
b11111011 1
b101 )
b101 0
1+
0'
#115000
b11 8
b101111111100000001 !
b101111111100000001 7
1'
#120000
b0 *
b0 1
b0 )
b0 0
0+
b10 .
b0 ,
0'
#125000
1'
#130000
b11111110 *
b11111110 1
b110 )
b110 0
1+
0'
#135000
b11 8
b101111111100000001 !
b101111111100000001 7
1'
#140000
b0 *
b0 1
b0 )
b0 0
0+
b1 ,
0'
#145000
1'
#150000
b110 *
b110 1
b111 )
b111 0
1+
0'
#155000
b11 8
b101111111100000001 !
b101111111100000001 7
1'
#160000
b0 *
b0 1
b0 )
b0 0
0+
b10 ,
0'
#165000
1'
#170000
b111 *
b111 1
b1000 )
b1000 0
1+
0'
#175000
b11 8
b101111111100000001 !
b101111111100000001 7
1'
#180000
b0 *
b0 1
b0 )
b0 0
0+
b11 .
b0 ,
0'
#185000
1'
#190000
b1000 *
b1000 1
b1001 )
b1001 0
1+
0'
#195000
b11 8
b101111111100000001 !
b101111111100000001 7
1'
#200000
b0 *
b0 1
b0 )
b0 0
0+
b1 ,
0'
#205000
1'
#210000
b11111101 *
b11111101 1
b1010 )
b1010 0
1+
0'
#215000
b11 8
b101111111100000001 !
b101111111100000001 7
1'
#220000
b0 *
b0 1
b0 )
b0 0
0+
b10 ,
0'
#225000
1'
#230000
b1011 )
b1011 0
1+
0'
#235000
b11 8
b101111111100000001 !
b101111111100000001 7
1'
#240000
b0 )
b0 0
0+
b0 .
b11 ,
0'
#241000
b11 ,
#245000
b11 8
b111110110000010000000011 !
b111110110000010000000011 7
b1 (
b1 /
b1 .
1'
#246000
b11 ,
#250000
0'
#255000
b11 8
b1110000011011111110 !
b1110000011011111110 7
b10 (
b10 /
b10 .
1'
#256000
b11 ,
#260000
0'
#265000
b11 8
b1111110100001000 !
b1111110100001000 7
b11 (
b11 /
b11 .
1'
#266000
b11 ,
#270000
0'
#275000
b100 .
1'
