GCollab/dla_controller.v
`timescale 1ns / 1ps

// Controller FSM for one matrix multiply transaction across K MAC cycles.
module dla_controller #(
    parameter K       = 4,
    parameter K_IDX_W = (K <= 1) ? 1 : $clog2(K)
) (
    input                      clk,
    input                      rst_n,
    input                      start,
    output reg                 clear_pe,
    output reg                 en_pe,
    output reg [K_IDX_W-1:0]   k_idx,
    output reg                 done,
    output reg                 busy
);

    localparam [1:0] S_IDLE    = 2'b00;
    localparam [1:0] S_CLEAR   = 2'b01;
    localparam [1:0] S_COMPUTE = 2'b10;
    localparam [1:0] S_DONE    = 2'b11;

    reg [1:0] state;
    reg [1:0] next_state;

    // Next-state logic.
    always @* begin
        next_state = state;

        case (state)
            S_IDLE: begin
                if (start) begin
                    next_state = S_CLEAR;
                end
            end

            S_CLEAR: begin
                next_state = S_COMPUTE;
            end

            S_COMPUTE: begin
                if (k_idx == (K-1)) begin
                    next_state = S_DONE;
                end
            end

            S_DONE: begin
                if (!start) begin
                    next_state = S_IDLE;
                end
            end

            default: begin
                next_state = S_IDLE;
            end
        endcase
    end

    // State and k-index update.
    always @(posedge clk or negedge rst_n) begin
        if (!rst_n) begin
            state <= S_IDLE;
            k_idx <= {K_IDX_W{1'b0}};
        end else begin
            state <= next_state;

            if ((state == S_IDLE) || (state == S_CLEAR)) begin
                k_idx <= {K_IDX_W{1'b0}};
            end else if ((state == S_COMPUTE) && (k_idx != (K-1))) begin
                k_idx <= k_idx + 1'b1;
            end
        end
    end

    // Control outputs are purely combinational from state.
    always @* begin
        clear_pe = (state == S_CLEAR);
        en_pe    = (state == S_COMPUTE);
        done     = (state == S_DONE);
        busy     = ((state == S_CLEAR) || (state == S_COMPUTE));
    end

endmodule

tb/dla_controller_tb.sv
`timescale 1ns / 1ps

module dla_controller_tb;

    localparam int K       = 4;
    localparam int K_IDX_W = (K <= 1) ? 1 : $clog2(K);

    logic               clk;
    logic               rst_n;
    logic               start;
    logic               clear_pe;
    logic               en_pe;
    logic [K_IDX_W-1:0] k_idx;
    logic               done;
    logic               busy;

    integer errors;
    integer clear_count;
    integer en_count;
    integer done_count;
    integer expected_k;

    dla_controller #(
        .K(K),
        .K_IDX_W(K_IDX_W)
    ) dut (
        .clk(clk),
        .rst_n(rst_n),
        .start(start),
        .clear_pe(clear_pe),
        .en_pe(en_pe),
        .k_idx(k_idx),
        .done(done),
        .busy(busy)
    );

    always #5 clk = ~clk;

    always @(posedge clk or negedge rst_n) begin
        if (!rst_n) begin
            clear_count <= 0;
            en_count    <= 0;
            done_count  <= 0;
            expected_k  <= 0;
        end else begin
            if (clear_pe) begin
                clear_count <= clear_count + 1;
            end

            if (en_pe) begin
                if (k_idx !== expected_k[K_IDX_W-1:0]) begin
                    errors <= errors + 1;
                    $display(
                        "[TB][FAIL] k_idx=%0d expected=%0d",
                        k_idx,
                        expected_k[K_IDX_W-1:0]
                    );
                end
                expected_k <= expected_k + 1;
                en_count   <= en_count + 1;
            end

            if (done) begin
                done_count <= done_count + 1;
            end
        end
    end

    task automatic pulse_start;
        begin
            @(negedge clk);
            start <= 1'b1;
            @(negedge clk);
            start <= 1'b0;
        end
    endtask

    task automatic run_transaction(input int txn_id);
        integer timeout;
        begin
            clear_count = 0;
            en_count    = 0;
            done_count  = 0;
            expected_k  = 0;

            pulse_start();

            timeout = 0;
            while (!done && (timeout < 40)) begin
                @(posedge clk);
                timeout = timeout + 1;
            end

            if (!done) begin
                errors = errors + 1;
                $display("[TB][FAIL][txn=%0d] timeout waiting for done", txn_id);
            end

            @(posedge clk);

            if (clear_count != 1) begin
                errors = errors + 1;
                $display("[TB][FAIL][txn=%0d] clear_count=%0d expected=1", txn_id, clear_count);
            end

            if (en_count != K) begin
                errors = errors + 1;
                $display("[TB][FAIL][txn=%0d] en_count=%0d expected=%0d", txn_id, en_count, K);
            end

            if (done_count < 1) begin
                errors = errors + 1;
                $display("[TB][FAIL][txn=%0d] done never asserted", txn_id);
            end

            if (busy) begin
                errors = errors + 1;
                $display("[TB][FAIL][txn=%0d] busy should deassert after done", txn_id);
            end
        end
    endtask

    initial begin
        $dumpfile("sim/results/dla_controller_tb.vcd");
        $dumpvars(0, dla_controller_tb);

        clk         = 1'b0;
        rst_n       = 1'b0;
        start       = 1'b0;
        errors      = 0;
        clear_count = 0;
        en_count    = 0;
        done_count  = 0;
        expected_k  = 0;

        repeat (3) @(posedge clk);
        rst_n = 1'b1;
        repeat (2) @(posedge clk);

        run_transaction(0);
        run_transaction(1);

        if (errors == 0) begin
            $display("[TB][PASS] dla_controller_tb passed.");
            $finish;
        end else begin
            $display("[TB][ERROR] dla_controller_tb mismatches=%0d", errors);
            $fatal(1);
        end
    end

endmodule

sim/results/dla_controller_tb.vcd
$date
	Sun Apr 19 06:06:24 2026
$end
$version
	Icarus Verilog
$end
$timescale
	1ps
$end
$scope module dla_controller_tb $end
$var wire 2 ! k_idx [1:0] $end
$var wire 1 " en_pe $end
$var wire 1 # done $end
$var wire 1 $ clear_pe $end
$var wire 1 % busy $end
$var parameter 32 & K $end
$var parameter 32 ' K_IDX_W $end
$var reg 1 ( clk $end
$var reg 1 ) rst_n $end
$var reg 1 * start $end
$var integer 32 + clear_count [31:0] $end
$var integer 32 , done_count [31:0] $end
$var integer 32 - en_count [31:0] $end
$var integer 32 . errors [31:0] $end
$var integer 32 / expected_k [31:0] $end
$scope module dut $end
$var wire 1 ( clk $end
$var wire 1 ) rst_n $end
$var wire 1 * start $end
$var parameter 32 0 K $end
$var parameter 32 1 K_IDX_W $end
$var parameter 2 2 S_CLEAR $end
$var parameter 2 3 S_COMPUTE $end
$var parameter 2 4 S_DONE $end
$var parameter 2 5 S_IDLE $end
$var reg 1 % busy $end
$var reg 1 $ clear_pe $end
$var reg 1 # done $end
$var reg 1 " en_pe $end
$var reg 2 6 k_idx [1:0] $end
$var reg 2 7 next_state [1:0] $end
$var reg 2 8 state [1:0] $end
$upscope $end
$scope task pulse_start $end
$upscope $end
$scope task run_transaction $end
$upscope $end
$upscope $end
$enddefinitions $end
$comment Show the parameter values. $end
$dumpall
b0 5
b11 4
b10 3
b1 2
b10 1
b100 0
b10 '
b100 &
$end
#0
$dumpvars
b0 8
b0 7
b0 6
b0 /
b0 .
b0 -
b0 ,
b0 +
0*
0)
0(
0%
0$
0#
0"
b0 !
$end
#5000
1(
#10000
0(
#15000
1(
#20000
0(
#25000
1)
1(
#30000
0(
#35000
1(
#40000
0(
#45000
1(
#50000
b1 7
1*
0(
#55000
1%
1$
b10 7
b1 8
1(
#60000
b10 7
0*
0(
#65000
1"
0$
b1 +
b10 8
1(
#70000
0(
#75000
b1 !
b1 6
b1 -
b1 /
1(
#80000
0(
#85000
b10 -
b10 /
b10 !
b10 6
1(
#90000
0(
#95000
b11 7
b11 !
b11 6
b11 -
b11 /
1(
#100000
0(
#105000
0%
1#
0"
b0 7
b100 -
b100 /
b11 8
1(
#110000
0(
#115000
0#
b0 8
b1 ,
1(
#120000
0(
#125000
b0 !
b0 6
b0 /
b0 ,
b0 -
b0 +
1(
#130000
b1 7
1*
0(
#135000
1%
1$
b10 7
b1 8
1(
#140000
b10 7
0*
0(
#145000
1"
0$
b1 +
b10 8
1(
#150000
0(
#155000
b1 !
b1 6
b1 -
b1 /
1(
#160000
0(
#165000
b10 -
b10 /
b10 !
b10 6
1(
#170000
0(
#175000
b11 7
b11 !
b11 6
b11 -
b11 /
1(
#180000
0(
#185000
0%
1#
0"
b0 7
b100 -
b100 /
b11 8
1(
#190000
0(
#195000
0#
b0 8
b1 ,
1(
#200000
0(
#205000
b0 !
b0 6
1(
